dyn/utils.py
dyn/core/__init__.py
dyn/core/aggregate_csv.py
dyn/core/communities.py
dyn/core/community_graphs.py
dyn/core/files_io.py
dyn_core-0.1.1.dist-info/licenses/LICENSE
dyn_core-0.1.1.dist-info/METADATA
dyn_core-0.1.1.dist-info/WHEEL
dyn_core-0.1.1.dist-info/top_level.txt
dyn_core-0.1.1.dist-info/RECORD
