Metadata-Version: 2.4
Name: dyn-core
Version: 0.1.1
Summary: Core features of the 'dyn' namespace package
Author-email: Cécile Bothorel <cecile.bothorel@imt-atlantique.fr>, Laurent Brisson <laurent.brisson@imt-atlantique.fr>, Nicolas Duminy <nicolas.duminy@imt-atlantique.fr>
License: Copyright IMT Atlantique, 2021
Project-URL: Homepage, https://gitlab.com/decide.imt-atlantique/dyn/core
Project-URL: Issues, https://gitlab.com/decide.imt-atlantique/dyn/core/issues
Project-URL: Documentation, https://dyn-core.readthedocs.io/en/latest/
Classifier: Development Status :: 4 - Beta
Classifier: Intended Audience :: Developers
Classifier: Intended Audience :: Science/Research
Classifier: License :: OSI Approved :: European Union Public Licence 1.2 (EUPL 1.2)
Classifier: Operating System :: OS Independent
Classifier: Programming Language :: Python :: 3
Classifier: Programming Language :: Python :: 3 :: Only
Requires-Python: >=3.8
License-File: LICENSE
Requires-Dist: networkx
Requires-Dist: pandas
Requires-Dist: nbformat
Requires-Dist: nbconvert
Requires-Dist: typing_extensions; python_version < "3.11"
Dynamic: license-file
